frappyflaskauth/__init__.py
frappyflaskauth/user_api.py
frappyflaskauth-1.6.3.dist-info/LICENSE
frappyflaskauth-1.6.3.dist-info/METADATA
frappyflaskauth-1.6.3.dist-info/WHEEL
frappyflaskauth-1.6.3.dist-info/top_level.txt
frappyflaskauth-1.6.3.dist-info/RECORD
