Metadata-Version: 2.1
Name: frappyflaskauth
Version: 1.6.3
Summary: Flask endpoints for user management and authentication.
Home-page: https://github.com/ilfrich/frappy-flask-authentication
Author: Peter Ilfrich
Author-email: das-peter@gmx.de
License-File: LICENSE
Requires-Dist: flask
Requires-Dist: pbu >=1.1.7
